kskimtestmodule/__init__.py
kskimtestmodule/circle.py
kskimtestmodule/rectangle.py
kskimtestmodule/testfunc.py
kskimtestmodule/testspark.py
kskimtestmodule-0.3.7.dist-info/LICENSE
kskimtestmodule-0.3.7.dist-info/METADATA
kskimtestmodule-0.3.7.dist-info/WHEEL
kskimtestmodule-0.3.7.dist-info/top_level.txt
kskimtestmodule-0.3.7.dist-info/RECORD
