Metadata-Version: 2.1
Name: kskimtestmodule
Version: 0.3.7
Summary: A simple Python library for test spark in zeppelin
Author: kisun3.kim
License-File: LICENSE
